tensorgram.py
tensorgram-0.0.7.dist-info/LICENSE
tensorgram-0.0.7.dist-info/METADATA
tensorgram-0.0.7.dist-info/WHEEL
tensorgram-0.0.7.dist-info/top_level.txt
tensorgram-0.0.7.dist-info/RECORD
