Metadata-Version: 2.1
Name: tensorgram
Version: 0.0.7
Summary: A realtime remote service to get the keras callbacks to the telegram including the details of metrics 
Home-page: https://github.com/ksdkamesh99/TensorGram
Author: Sai Durga Kamesh Kota
Author-email: ksdkamesh99@gmail.com
License: UNKNOWN
Platform: UNKNOWN
Classifier: Programming Language :: Python :: 3
Classifier: License :: OSI Approved :: MIT License
Classifier: Operating System :: OS Independent
Requires-Python: >=3.6
Requires-Dist: keras (>=2.4)
Requires-Dist: tensorflow (>=2.3)
Requires-Dist: matplotlib (>=3.2)
Requires-Dist: requests
